MyClickUp/MyClickUp.py
MyClickUp/__init__.py
MyClickUp-0.1.5.dist-info/LICENSE
MyClickUp-0.1.5.dist-info/METADATA
MyClickUp-0.1.5.dist-info/WHEEL
MyClickUp-0.1.5.dist-info/top_level.txt
MyClickUp-0.1.5.dist-info/RECORD
