Metadata-Version: 2.1
Name: MyClickUp
Version: 0.1.5
Summary: The MyClickUp class allows you to encapsulate the integration with the ClickUp API
Home-page: UNKNOWN
Author: Jose Cordeiro
License: MIT
Platform: UNKNOWN
License-File: LICENSE
